lazym/__init__.py
lazym/chain.py
lazym/cli.py
lazym/configs.py
lazym/constants.py
lazym/git.py
lazym/github.py
lazym/prepare-commit-msg
lazym/prompt.py
lazym/version.py
lazym-0.22.0.dist-info/LICENSE
lazym-0.22.0.dist-info/METADATA
lazym-0.22.0.dist-info/WHEEL
lazym-0.22.0.dist-info/entry_points.txt
lazym-0.22.0.dist-info/top_level.txt
lazym-0.22.0.dist-info/RECORD
