Metadata-Version: 2.2
Name: lazym
Version: 0.22.0
Summary: A tool to generate commit messages using AI
Home-page: https://github.com/spitfire-sidra/lazym
Author: Amo Chen
Author-email: chimerhapsody@gmail.com
Classifier: Development Status :: 3 - Alpha
Classifier: Intended Audience :: Developers
Classifier: License :: OSI Approved :: MIT License
Classifier: Operating System :: OS Independent
Classifier: Programming Language :: Python :: 3
Classifier: Programming Language :: Python :: 3.7
Classifier: Programming Language :: Python :: 3.8
Classifier: Programming Language :: Python :: 3.9
Classifier: Programming Language :: Python :: 3.10
Classifier: Programming Language :: Python :: 3.11
Classifier: Programming Language :: Python :: 3.12
Requires-Python: >=3.7
License-File: LICENSE
Requires-Dist: langchain==0.3.3
Requires-Dist: langchain-community==0.3.2
Requires-Dist: langchain-core==0.3.10
Requires-Dist: langchain-ollama==0.2.0
Requires-Dist: langchain-groq==0.2.0
Requires-Dist: langchain-text-splitters==0.3.0
Requires-Dist: beaupy==3.9.2
Requires-Dist: prompt_toolkit==3.0.48
Requires-Dist: pyperclip==1.9.0
Requires-Dist: halo==0.0.31
Requires-Dist: typer==0.12.5
Requires-Dist: prettytable==3.14.0
Dynamic: author
Dynamic: author-email
Dynamic: classifier
Dynamic: description
Dynamic: description-content-type
Dynamic: home-page
Dynamic: requires-dist
Dynamic: requires-python
Dynamic: summary
